coinmarketcap/__init__.py
coinmarketcap/clients.py
coinmarketcap/constants.py
coinmarketcap/exceptions.py
coinmarketcap/parsers.py
coinmarketcap/tests/__init__.py
coinmarketcap/tests/test_clients.py
coinmarketcap/tests/test_parsers.py
coinmarketcap_client-2.5.3.dist-info/METADATA
coinmarketcap_client-2.5.3.dist-info/RECORD
coinmarketcap_client-2.5.3.dist-info/WHEEL
coinmarketcap_client-2.5.3.dist-info/top_level.txt
