Metadata-Version: 2.1
Name: coinmarketcap-client
Version: 2.5.3
Summary: Python Coin Market Cap Client
Home-page: https://gitlab.com/pgrangeiro/python-coinmarketcap-client
Author: Paula Grangeiro
Author-email: contato@paulagrangeiro.com.br
License: GNU General Public License v3.0
Download-URL: https://gitlab.com/pgrangeiro/python-coinmarketcap-client/-/archive/master/python-coinmarketcap-client-master.tar.gz
Keywords: coinmarketcap,cryptocurrency,cryptocoin
Platform: UNKNOWN
Requires-Python: >=3.6
